setup.py
xheadtail/__init__.py
xheadtail/_version.py
xheadtail.egg-info/PKG-INFO
xheadtail.egg-info/SOURCES.txt
xheadtail.egg-info/dependency_links.txt
xheadtail.egg-info/requires.txt
xheadtail.egg-info/top_level.txt